[
  {
    "$type": "ModListMetadata, Wabbajack.Lib",
    "title": "The Northern Experience",
    "description": "Mod list that will provide a unique, Gothic-esque adventure.",
    "author": "mnikjom",
    "maintainers": [
      "github/mnikjom"
    ],
    "game": "skyrimspecialedition",
    "official": true,
    "tags": [
      "Official"
    ],
    "nsfw": false,
    "image_contains_title": true,
    "force_down": false,
    "links": {
      "$type": "Links, Wabbajack.Lib",
      "image": "https://staticdelivery.nexusmods.com/mods/1704/images/23894/23894-1578511882-321812591.jpeg",
      "readme": "https://www.nexusmods.com/skyrimspecialedition/mods/69147",
      "download": "https://authored-files.wabbajack.org/The%20Northern%20Experience.wabbajack_ac99554f-092c-4714-9061-81ece7450e30",
      "machineURL": "tne",
      "discordURL": "https://discord.gg/fuhsnph"
    },
    "download_metadata": {
      "$type": "DownloadMetadata, Wabbajack.Lib",
      "Hash": "GkQIyQrAqAQ=",
      "Size": 511898622,
      "NumberOfArchives": 3081,
      "SizeOfArchives": 143005480707,
      "NumberOfInstalledFiles": 194897,
      "SizeOfInstalledFiles": 218944522598
    },
    "version": "1.6.6"
  }
]
